luoshu_python_sdk-0.1.0.dist-info/METADATA
luoshu_python_sdk-0.1.0.dist-info/WHEEL
luoshu_python_sdk/__init__.py
luoshu_python_sdk/luoshu_python_sdk.pypy38-pp73-x86_64-linux-gnu.so
luoshu_python_sdk-0.1.0.dist-info/RECORD
