Metadata-Version: 2.1
Name: luoshu-python-sdk
Version: 0.1.0
Summary: Luoshu
